pygments_michelson/__init__.py
pygments_michelson/michelson_lexer.py
pygments_michelson-1.0.1.dist-info/LICENSE
pygments_michelson-1.0.1.dist-info/METADATA
pygments_michelson-1.0.1.dist-info/WHEEL
pygments_michelson-1.0.1.dist-info/entry_points.txt
pygments_michelson-1.0.1.dist-info/top_level.txt
pygments_michelson-1.0.1.dist-info/RECORD
