Metadata-Version: 2.1
Name: pygments-michelson
Version: 1.0.1
Summary: Pygments lexer for Michelson contracts
Home-page: https://gitlab.com/arvidnl/pygments-michelson
Author: Arvid Jakobsson
Author-email: arvid.jakobsson@nomadic-labs.com
License: MIT
Keywords: pygments michelson tezos lexer
Platform: UNKNOWN
Classifier: Programming Language :: Python :: 3
Classifier: License :: OSI Approved :: MIT License
Requires-Python: >=3.4
Requires-Dist: Pygments (>=2)
